LICENSE
MANIFEST.in
README.md
setup.py
slugify/__init__.py
slugify/tests.py
unicode_slugify_latin.egg-info/PKG-INFO
unicode_slugify_latin.egg-info/SOURCES.txt
unicode_slugify_latin.egg-info/dependency_links.txt
unicode_slugify_latin.egg-info/not-zip-safe
unicode_slugify_latin.egg-info/requires.txt
unicode_slugify_latin.egg-info/top_level.txt