Metadata-Version: 1.1
Name: unicode-slugify-latin
Version: 0.2
Summary: A slug generator that turns strings into unicode slugs, and enables replacement for common latin letters into ascii representations.
Home-page: http://github.com/eminbugrasaral/unicode-slugify-latin
Author: Emin Bugra Saral
Author-email: eminbugrasaral@me.com
License: BSD
Keywords: turkish,latin,unicode,slugify,letter,char,replace,replacement,ascii,django
Platform: UNKNOWN
Classifier: Development Status :: 4 - Beta
Classifier: Environment :: Web Environment
Classifier: Environment :: Web Environment :: Mozilla
Classifier: Intended Audience :: Developers
Classifier: License :: OSI Approved :: BSD License
Classifier: Operating System :: OS Independent
Classifier: Programming Language :: Python
Classifier: Programming Language :: Python :: 2.6
Classifier: Programming Language :: Python :: 2.7
Classifier: Programming Language :: Python :: 3.3
Classifier: Topic :: Software Development :: Libraries :: Python Modules
Classifier: Framework :: Django
